smalltime/__init__.py
smalltime/cli.py
smalltime/timer.py
smalltime-0.0.7.dist-info/entry_points.txt
smalltime-0.0.7.dist-info/LICENSE
smalltime-0.0.7.dist-info/WHEEL
smalltime-0.0.7.dist-info/METADATA
smalltime-0.0.7.dist-info/RECORD
