Metadata-Version: 2.1
Name: smalltime
Version: 0.0.7
Summary: A small python timing package for a packaging demonstration
License: BSD 3-Clause
Author: nicklambourne
Author-email: dev@ndl.im
Requires-Python: >=3.6.2,<4.0.0
Classifier: Development Status :: 3 - Alpha
Classifier: Intended Audience :: Developers
Classifier: License :: OSI Approved :: BSD License
Classifier: License :: Other/Proprietary License
Classifier: Programming Language :: Python :: 3
Classifier: Programming Language :: Python :: 3 :: Only
Classifier: Programming Language :: Python :: 3.10
Classifier: Programming Language :: Python :: 3.6
Classifier: Programming Language :: Python :: 3.7
Classifier: Programming Language :: Python :: 3.8
Classifier: Programming Language :: Python :: 3.9
Classifier: Programming Language :: Python :: Implementation :: CPython
Classifier: Topic :: Software Development :: Libraries :: Python Modules
Provides-Extra: docs
Requires-Dist: ansicolors (>=1.1.8,<2.0.0)
Requires-Dist: shortuuid (>=1.0.1,<2.0.0)
